<?xml version="1.0" encoding="utf-8" ?>
<dwsync>
<file name="bg.gif" local="130754646868856273" remote="130775872200000000" testing="0" />
<file name="table.css" local="130776153895064792" remote="130775872200000000" testing="0" />
<file name="__server.php" local="130789106970082841" remote="130788819000000000" testing="0" />
<file name="brantch.gif" local="130754649988671872" remote="130775872200000000" testing="0" />
<file name="brantch.png" local="130754646698586534" remote="130775872200000000" testing="0" />
<file name="config.php" local="130724207607649655" remote="130775872200000000" testing="0" />
<file name="get_input.php" local="130730349058473494" remote="130775872200000000" testing="0" />
<file name="get_sub_data.php" local="130772689247730363" remote="130775872200000000" testing="0" />
<file name="table.def.php" local="130730383420418885" remote="130775872200000000" testing="0" />
<file name="table.tag.php" local="130789096578828495" remote="130788808800000000" testing="0" />
<file name="update_column.php" local="130730417924092382" remote="130775872200000000" testing="0" />
<file name="log.txt" local="130778422200000000" remote="130778422200000000" testing="0" />
</dwsync>